CHANGES.txt
MANIFEST.in
README.rst
setup.py
imsvdex/__init__.py
imsvdex/vdex.py
imsvdex/vdex.txt
imsvdex.egg-info/PKG-INFO
imsvdex.egg-info/SOURCES.txt
imsvdex.egg-info/dependency_links.txt
imsvdex.egg-info/not-zip-safe
imsvdex.egg-info/requires.txt
imsvdex.egg-info/top_level.txt
imsvdex/tests/__init__.py
imsvdex/tests/test.xml
imsvdex/tests/testConverters.py
imsvdex/tests/testDoctests.py