Metadata-Version: 1.1
Name: imsvdex
Version: 1.2
Summary: Read/write vocabularies in IMS Vocabulary Definition Exchange format.
Home-page: https://github.com/collective/imsvdex
Author: Martin Raspe
Author-email: raspe@biblhertz.it
License: D-FSL - German Free Software License
Keywords: vocabulary xml vdex ims
Platform: UNKNOWN
Classifier: Development Status :: 5 - Production/Stable
Classifier: Intended Audience :: Developers
Classifier: Operating System :: OS Independent
Classifier: Programming Language :: Python :: 2.7
Classifier: Programming Language :: Python :: 3.6
Classifier: Programming Language :: Python :: 3.7
Classifier: Programming Language :: Python :: 3.8
Classifier: Programming Language :: Python
Classifier: Topic :: Software Development :: Libraries :: Python Modules
